{"noiseKey":{"private":{"type":"Buffer","data":"sBb1fgrgiyeLrcqiicMjAhh9KCjB7BOu0tOUeIWZl1s="},"public":{"type":"Buffer","data":"xtAxe/FjLbZLxEy8LVgqMYZXDiWRiuYnqQirnZokE3M="}},"pairingEphemeralKeyPair":{"private":{"type":"Buffer","data":"+MFgTXBKVmQf82S3+3OV3VpD6vxrAqnESNaIcXKgNms="},"public":{"type":"Buffer","data":"9BDq1FkzZ+Ix1bwLnXDHHr1rP31KuL16OM3iUuGL8zg="}},"signedIdentityKey":{"private":{"type":"Buffer","data":"aLwOOis8D45nw7+ypsgrH98eJ59aunAtK4eYOOB3J0Q="},"public":{"type":"Buffer","data":"mkuvSscwYLAV4F/ZGfAWstq+vHhdCfEDKuc7RvtvQFQ="}},"signedPreKey":{"keyPair":{"private":{"type":"Buffer","data":"OJVCJlhzlbnp5zp3xcvYu8zVAI0b7a0z/iTosZoPcEU="},"public":{"type":"Buffer","data":"+RZDWIiSdgUGgRcerkQLkskzv4pv2PLUNtRCvgZKYSM="}},"signature":{"type":"Buffer","data":"k9NPIr/fCfAgtztjUQ/IaEhFktbzEg4rglmQu7H1GHX3p1zh7YC4k4T8PH39S1RP6DDliZPCnuonvrXCmCi6jA=="},"keyId":1},"registrationId":5,"advSecretKey":"J9pTVleBbHqx6RG7nSy62NoRrVM5jlr0m7HAxukVq1Q=","processedHistoryMessages":[{"key":{"remoteJid":"919775111374@s.whatsapp.net","fromMe":true,"id":"A515CB5D02FD6178B9B412EFC054DCDD"},"messageTimestamp":1762353619},{"key":{"remoteJid":"919775111374@s.whatsapp.net","fromMe":true,"id":"A5A175B9A86ABB5A45BB5883903C7318"},"messageTimestamp":1762353626},{"key":{"remoteJid":"919775111374@s.whatsapp.net","fromMe":true,"id":"A5F2A35730ABEEC818152FBC64FDAB0F"},"messageTimestamp":1762353661},{"key":{"remoteJid":"919775111374@s.whatsapp.net","fromMe":true,"id":"A5C02CE77FDCEE0A635B22B5C8F1ADFA"},"messageTimestamp":1762353697},{"key":{"remoteJid":"919775111374@s.whatsapp.net","fromMe":true,"id":"A5F2552F73BB6A4E2ED073E0BC396EC2"},"messageTimestamp":1762353719},{"key":{"remoteJid":"919775111374@s.whatsapp.net","fromMe":true,"id":"A50FD6F4850E47AEA2F74C065C8AE521"},"messageTimestamp":1762353785},{"key":{"remoteJid":"919775111374@s.whatsapp.net","fromMe":true,"id":"A5E4452152CCF48FC66C75083FA6CFA2"},"messageTimestamp":1762353808},{"key":{"remoteJid":"919775111374@s.whatsapp.net","fromMe":true,"id":"A54A1478CEFCD21A14F0E0EE05DE8818"},"messageTimestamp":1762353844},{"key":{"remoteJid":"919775111374@s.whatsapp.net","fromMe":true,"id":"A543D9480433035CD45FCAAAFF19B5D6"},"messageTimestamp":1762353877},{"key":{"remoteJid":"919775111374@s.whatsapp.net","fromMe":true,"id":"A5F41C5E9CF63E6BE143ACE606087E00"},"messageTimestamp":1762353896},{"key":{"remoteJid":"919775111374@s.whatsapp.net","fromMe":true,"id":"A5471D597B46FD56796E4E6E59B159E3"},"messageTimestamp":1762353913},{"key":{"remoteJid":"919775111374@s.whatsapp.net","fromMe":true,"id":"A5741130D55DA33E550861E58B0C54E6"},"messageTimestamp":1762353932},{"key":{"remoteJid":"919775111374@s.whatsapp.net","fromMe":true,"id":"A561FFB3524D2D84ADFC1B0FC71027B6"},"messageTimestamp":1762353947},{"key":{"remoteJid":"919775111374@s.whatsapp.net","fromMe":true,"id":"A5D732083D10099030DD6E02EE85813D"},"messageTimestamp":1762353958},{"key":{"remoteJid":"919775111374@s.whatsapp.net","fromMe":true,"id":"A5D9BC374150928331433AB70EAE13C4"},"messageTimestamp":1762353971},{"key":{"remoteJid":"919775111374@s.whatsapp.net","fromMe":true,"id":"A53D22CFB4E8357BF50974954CFB2339"},"messageTimestamp":1762353992},{"key":{"remoteJid":"919775111374@s.whatsapp.net","fromMe":true,"id":"A544524D52BB1050F677C87BCB26C552"},"messageTimestamp":1762354021},{"key":{"remoteJid":"919775111374@s.whatsapp.net","fromMe":true,"id":"A594861996F418136EC9AEA30FC3109A"},"messageTimestamp":1762354888}],"nextPreKeyId":34,"firstUnuploadedPreKeyId":34,"accountSyncCounter":1,"accountSettings":{"unarchiveChats":false},"deviceId":"20CpZBcmSOi82i8KxEpp4A","phoneId":"c36e3090-9f71-4b33-b5af-625a7ec360cd","identityId":{"type":"Buffer","data":"0L/DoUg8H3wyPUXAdWZvf7wjPjk="},"registered":true,"backupToken":{"type":"Buffer","data":"n1pBc89Cz3tQ2rSN9DehbZyHG4M="},"registration":{},"pairingCode":"CQD8LB52","me":{"id":"919775111374:8@s.whatsapp.net","name":"// 𝙷𝚄𝚂𝙱𝙰𝙽𝙳 ! //","lid":"76743197110389:8@lid"},"account":{"details":"CNWAjsoHELvDrcgGGAMgACgA","accountSignatureKey":"72Agjs3QVoLzEEhMfOdhu/jLR+8+rR+k7oK4Au3qQB8=","accountSignature":"bnN199XliCQCHxJyK2omGNdPZQ5laJNm1wr7kSCpdicodOPbBacbCUgryWlYpuyKbvtocrZeCVvDwPuv86tbDw==","deviceSignature":"/T/axbI1PuITfuSegfQbTGkIr94ZsIcYsp4dJTTys8yYdvY/Teq2zcZMHeTLNI+0AxV3VdRYSaRvhBNuGpjoiA=="},"signalIdentities":[{"identifier":{"name":"919775111374:8@s.whatsapp.net","deviceId":0},"identifierKey":{"type":"Buffer","data":"Be9gII7N0FaC8xBITHznYbv4y0fvPq0fpO6CuALt6kAf"}}],"platform":"smba","routingInfo":{"type":"Buffer","data":"CBIIBQ=="},"lastAccountSyncTimestamp":1762353609,"lastPropHash":"C4fJN","myAppStateKeyId":"AAAAAB/S"}